dictpress/VERSION
dictpress/__init__.py
dictpress-0.3.0.dist-info/LICENSE
dictpress-0.3.0.dist-info/METADATA
dictpress-0.3.0.dist-info/WHEEL
dictpress-0.3.0.dist-info/RECORD
