Metadata-Version: 2.3
Name: dictpress
Version: 0.3.0
Summary: A Python library designed for deep-merging, updating, and compressing dictionaries.
License: MIT
Author: Allen Chou
Author-email: f1470891079@gmail.com
Requires-Python: >=3.11,<4
Classifier: License :: OSI Approved :: MIT License
Classifier: Programming Language :: Python :: 3
Classifier: Programming Language :: Python :: 3.11
Classifier: Programming Language :: Python :: 3.12
Classifier: Programming Language :: Python :: 3.13
Provides-Extra: all
Project-URL: Homepage, https://github.com/allen2c/dictpress
Project-URL: PyPI, https://pypi.org/project/dictpress/
Project-URL: Repository, https://github.com/allen2c/dictpress
